gradientmessagebox/__init__.py
gradientmessagebox-1.5.dist-info/WHEEL
gradientmessagebox-1.5.dist-info/METADATA
gradientmessagebox-1.5.dist-info/RECORD
