Metadata-Version: 2.1
Name: gradientmessagebox
Version: 1.5
Summary: A very simple tkinter prompt window with an animated gradient background, By: Fibo Metavinci
Author-email: Fibo Metavinci <pszdw-75nat-5227i-bha5s-y7lai-pebdq-o2agp-3xho4-hd6z6-emxrd-nqe@dmail.ai>
Requires-Dist: certifi==2024.2.2
Requires-Dist: charset-normalizer==3.3.2
Requires-Dist: colour==0.1.5
Requires-Dist: docutils==0.21.2
Requires-Dist: idna==3.7
Requires-Dist: pillow==10.3.0
Requires-Dist: pyperclip==1.8.2
Requires-Dist: tomli_w==1.0.0
Project-URL: Home, https://github.com/inviti8/gradientmessagebox
